oss2/__init__.py
oss2/api.py
oss2/auth.py
oss2/compat.py
oss2/crc64_combine.py
oss2/credentials.py
oss2/crypto.py
oss2/crypto_bucket.py
oss2/defaults.py
oss2/exceptions.py
oss2/headers.py
oss2/http.py
oss2/iterators.py
oss2/models.py
oss2/resumable.py
oss2/select_params.py
oss2/select_response.py
oss2/task_queue.py
oss2/utils.py
oss2/xml_utils.py
alibabacloud_oss2-2.18.2.dist-info/LICENSE
alibabacloud_oss2-2.18.2.dist-info/METADATA
alibabacloud_oss2-2.18.2.dist-info/WHEEL
alibabacloud_oss2-2.18.2.dist-info/top_level.txt
alibabacloud_oss2-2.18.2.dist-info/RECORD
