Metadata-Version: 2.1
Name: alibabacloud-oss2
Version: 2.18.2
Summary: AlibabaCloud OSS SDK
Home-page: 
Classifier: Development Status :: 5 - Production/Stable
Classifier: Intended Audience :: Developers
Classifier: License :: OSI Approved :: Apache Software License
Classifier: Operating System :: OS Independent
Classifier: Programming Language :: Python
Classifier: Programming Language :: Python :: 2
Classifier: Programming Language :: Python :: 2.6
Classifier: Programming Language :: Python :: 2.7
Classifier: Programming Language :: Python :: 3
Classifier: Programming Language :: Python :: 3.3
Classifier: Programming Language :: Python :: 3.4
Classifier: Programming Language :: Python :: 3.5
Classifier: Programming Language :: Python :: 3.6
Classifier: Programming Language :: Python :: 3.7
Classifier: Programming Language :: Python :: 3.8
License-File: LICENSE
Requires-Dist: requests (!=2.9.0)
Requires-Dist: crcmod (>=1.7)
Requires-Dist: pycryptodome (>=3.4.7)
Requires-Dist: aliyun-python-sdk-kms (>=2.4.1)
Requires-Dist: python-alibabacloud-sdk-core (>=2.14.0)
Requires-Dist: six
